inputhandler/__init__.py
inputhandler/buffer_input.py
inputhandler/constant.py
inputhandler/getch.py
inputhandler/getwch.py
inputhandler/input_types.py
inputhandler/stdin.py
pyinputhandler-1.3.0.dist-info/LICENSE
pyinputhandler-1.3.0.dist-info/METADATA
pyinputhandler-1.3.0.dist-info/WHEEL
pyinputhandler-1.3.0.dist-info/top_level.txt
pyinputhandler-1.3.0.dist-info/RECORD
