Metadata-Version: 2.1
Name: pyinputhandler
Version: 1.3.0
Summary: A (basic) cross-platform python input handler
Home-page: https://github.com/DaHunterTime/InputHandler
Author: DaHunterTime
License: MIT
Project-URL: Bug Tracker, https://github.com/DaHunterTime/InputHandler/issues
Classifier: Programming Language :: Python :: 3
Classifier: License :: OSI Approved :: MIT License
Classifier: Operating System :: OS Independent
Requires-Python: >=3.7
License-File: LICENSE
